SemanticShield/__init__.py
SemanticShield/config_defaults.py
SemanticShield/dummy_data.py
SemanticShield/errors.py
SemanticShield/llm_result.py
SemanticShield/openai_funcs.py
SemanticShield/openai_model.py
SemanticShield/openai_settings.py
SemanticShield/pii_analyzer.py
SemanticShield/prompts.py
SemanticShield/rb_generator.py
SemanticShield/shield.py
SemanticShield/shield_config.py
SemanticShield/shield_result.py
SemanticShield/supported_entities.py
SemanticShield/yaml_parser.py
SemanticShield/fakers/__init__.py
SemanticShield/fakers/canadian_card_provider.py
SemanticShield/profanity/__init__.py
SemanticShield/profanity/profanity.py
SemanticShield/recognizers/__init__.py
SemanticShield/recognizers/canadian_bank_acct_recognizer.py
SemanticShield/recognizers/canadian_passport_recognizer.py
SemanticShield/recognizers/canadian_sin_recognizer.py
SemanticShield/recognizers/luhn.py
SemanticShield/recognizers/ontario_driver_license_recognizer.py
SemanticShield/recognizers/ontario_health_card_recognizer.py
SemanticShield/sensitive/__init__.py
SemanticShield/sensitive/passwords.py
SemanticShield/wrappers/__init__.py
SemanticShield/wrappers/openai_wrapper.py
SemanticShield-0.1.10.dist-info/LICENSE
SemanticShield-0.1.10.dist-info/METADATA
SemanticShield-0.1.10.dist-info/WHEEL
SemanticShield-0.1.10.dist-info/top_level.txt
SemanticShield-0.1.10.dist-info/RECORD
