Metadata-Version: 2.1
Name: SemanticShield
Version: 0.1.10
Summary: SemanticShield library
Home-page: https://github.com/SemanticBrainCorp/SemanticShield
Author: SemanticBrain
Author-email: info@semanticbrain.net
License: MIT
Project-URL: Bug Tracker, https://github.com/SemanticBrainCorp/SemanticShield/issues
Classifier: Programming Language :: Python :: 3
Classifier: License :: OSI Approved :: MIT License
Classifier: Operating System :: OS Independent
Requires-Python: >=3.9
License-File: LICENSE
Requires-Dist: openai ==0.28.0
Requires-Dist: spacy ==3.6.1
Requires-Dist: Faker ==19.6.1
Requires-Dist: presidio-analyzer ==2.2.33
Requires-Dist: exrex ==0.11.0
Requires-Dist: better-profanity ==0.7.0
Requires-Dist: alt-profanity-check ==1.3.1
